{"lines":[{"words":[{"t":"۞ قَالَ","c":"w"},{"t":"أَلَمْ","c":"w"},{"t":"أَقُل","c":"w"},{"t":"لَّكَ","c":"w"},{"t":"إِنَّكَ","c":"w"},{"t":"لَن","c":"w"},{"t":"تَسْتَطِيعَ","c":"w"},{"t":"مَعِىَ","c":"w"},{"t":"صَبْرًۭا","c":"w"},{"t":"٧٥","c":"e"},{"t":"قَالَ","c":"w"},{"t":"إِن","c":"w"}]},{"words":[{"t":"سَأَلْتُكَ","c":"w"},{"t":"عَن","c":"w"},{"t":"شَىْءٍۭ","c":"w"},{"t":"بَعْدَهَا","c":"w"},{"t":"فَلَا","c":"w"},{"t":"تُصَـٰحِبْنِى ۖ","c":"w"},{"t":"قَدْ","c":"w"},{"t":"بَلَغْتَ","c":"w"},{"t":"مِن","c":"w"},{"t":"لَّدُنِّى","c":"w"},{"t":"عُذْرًۭا","c":"w"}]},{"words":[{"t":"٧٦","c":"e"},{"t":"فَٱنطَلَقَا","c":"w"},{"t":"حَتَّىٰٓ","c":"w"},{"t":"إِذَآ","c":"w"},{"t":"أَتَيَآ","c":"w"},{"t":"أَهْلَ","c":"w"},{"t":"قَرْيَةٍ","c":"w"},{"t":"ٱسْتَطْعَمَآ","c":"w"},{"t":"أَهْلَهَا","c":"w"},{"t":"فَأَبَوْا۟","c":"w"}]},{"words":[{"t":"أَن","c":"w"},{"t":"يُضَيِّفُوهُمَا","c":"w"},{"t":"فَوَجَدَا","c":"w"},{"t":"فِيهَا","c":"w"},{"t":"جِدَارًۭا","c":"w"},{"t":"يُرِيدُ","c":"w"},{"t":"أَن","c":"w"},{"t":"يَنقَضَّ","c":"w"},{"t":"فَأَقَامَهُۥ ۖ","c":"w"}]},{"words":[{"t":"قَالَ","c":"w"},{"t":"لَوْ","c":"w"},{"t":"شِئْتَ","c":"w"},{"t":"لَتَّخَذْتَ","c":"w"},{"t":"عَلَيْهِ","c":"w"},{"t":"أَجْرًۭا","c":"w"},{"t":"٧٧","c":"e"},{"t":"قَالَ","c":"w"},{"t":"هَـٰذَا","c":"w"},{"t":"فِرَاقُ","c":"w"},{"t":"بَيْنِى","c":"w"}]},{"words":[{"t":"وَبَيْنِكَ ۚ","c":"w"},{"t":"سَأُنَبِّئُكَ","c":"w"},{"t":"بِتَأْوِيلِ","c":"w"},{"t":"مَا","c":"w"},{"t":"لَمْ","c":"w"},{"t":"تَسْتَطِع","c":"w"},{"t":"عَّلَيْهِ","c":"w"},{"t":"صَبْرًا","c":"w"},{"t":"٧٨","c":"e"},{"t":"أَمَّا","c":"w"}]},{"words":[{"t":"ٱلسَّفِينَةُ","c":"w"},{"t":"فَكَانَتْ","c":"w"},{"t":"لِمَسَـٰكِينَ","c":"w"},{"t":"يَعْمَلُونَ","c":"w"},{"t":"فِى","c":"w"},{"t":"ٱلْبَحْرِ","c":"w"},{"t":"فَأَرَدتُّ","c":"w"},{"t":"أَنْ","c":"w"},{"t":"أَعِيبَهَا","c":"w"}]},{"words":[{"t":"وَكَانَ","c":"w"},{"t":"وَرَآءَهُم","c":"w"},{"t":"مَّلِكٌۭ","c":"w"},{"t":"يَأْخُذُ","c":"w"},{"t":"كُلَّ","c":"w"},{"t":"سَفِينَةٍ","c":"w"},{"t":"غَصْبًۭا","c":"w"},{"t":"٧٩","c":"e"},{"t":"وَأَمَّا","c":"w"},{"t":"ٱلْغُلَـٰمُ","c":"w"}]},{"words":[{"t":"فَكَانَ","c":"w"},{"t":"أَبَوَاهُ","c":"w"},{"t":"مُؤْمِنَيْنِ","c":"w"},{"t":"فَخَشِينَآ","c":"w"},{"t":"أَن","c":"w"},{"t":"يُرْهِقَهُمَا","c":"w"},{"t":"طُغْيَـٰنًۭا","c":"w"},{"t":"وَكُفْرًۭا","c":"w"}]},{"words":[{"t":"٨٠","c":"e"},{"t":"فَأَرَدْنَآ","c":"w"},{"t":"أَن","c":"w"},{"t":"يُبْدِلَهُمَا","c":"w"},{"t":"رَبُّهُمَا","c":"w"},{"t":"خَيْرًۭا","c":"w"},{"t":"مِّنْهُ","c":"w"},{"t":"زَكَوٰةًۭ","c":"w"},{"t":"وَأَقْرَبَ","c":"w"},{"t":"رُحْمًۭا","c":"w"}]},{"words":[{"t":"٨١","c":"e"},{"t":"وَأَمَّا","c":"w"},{"t":"ٱلْجِدَارُ","c":"w"},{"t":"فَكَانَ","c":"w"},{"t":"لِغُلَـٰمَيْنِ","c":"w"},{"t":"يَتِيمَيْنِ","c":"w"},{"t":"فِى","c":"w"},{"t":"ٱلْمَدِينَةِ","c":"w"},{"t":"وَكَانَ","c":"w"}]},{"words":[{"t":"تَحْتَهُۥ","c":"w"},{"t":"كَنزٌۭ","c":"w"},{"t":"لَّهُمَا","c":"w"},{"t":"وَكَانَ","c":"w"},{"t":"أَبُوهُمَا","c":"w"},{"t":"صَـٰلِحًۭا","c":"w"},{"t":"فَأَرَادَ","c":"w"},{"t":"رَبُّكَ","c":"w"},{"t":"أَن","c":"w"},{"t":"يَبْلُغَآ","c":"w"}]},{"words":[{"t":"أَشُدَّهُمَا","c":"w"},{"t":"وَيَسْتَخْرِجَا","c":"w"},{"t":"كَنزَهُمَا","c":"w"},{"t":"رَحْمَةًۭ","c":"w"},{"t":"مِّن","c":"w"},{"t":"رَّبِّكَ ۚ","c":"w"},{"t":"وَمَا","c":"w"},{"t":"فَعَلْتُهُۥ","c":"w"}]},{"words":[{"t":"عَنْ","c":"w"},{"t":"أَمْرِى ۚ","c":"w"},{"t":"ذَٰلِكَ","c":"w"},{"t":"تَأْوِيلُ","c":"w"},{"t":"مَا","c":"w"},{"t":"لَمْ","c":"w"},{"t":"تَسْطِع","c":"w"},{"t":"عَّلَيْهِ","c":"w"},{"t":"صَبْرًۭا","c":"w"},{"t":"٨٢","c":"e"},{"t":"وَيَسْـَٔلُونَكَ","c":"w"}]},{"words":[{"t":"عَن","c":"w"},{"t":"ذِى","c":"w"},{"t":"ٱلْقَرْنَيْنِ ۖ","c":"w"},{"t":"قُلْ","c":"w"},{"t":"سَأَتْلُوا۟","c":"w"},{"t":"عَلَيْكُم","c":"w"},{"t":"مِّنْهُ","c":"w"},{"t":"ذِكْرًا","c":"w"},{"t":"٨٣","c":"e"}]}]}