{"lines":[{"words":[{"t":"لَّقَدْ","c":"w"},{"t":"سَمِعَ","c":"w"},{"t":"ٱللَّهُ","c":"w"},{"t":"قَوْلَ","c":"w"},{"t":"ٱلَّذِينَ","c":"w"},{"t":"قَالُوٓا۟","c":"w"},{"t":"إِنَّ","c":"w"},{"t":"ٱللَّهَ","c":"w"},{"t":"فَقِيرٌۭ","c":"w"},{"t":"وَنَحْنُ","c":"w"},{"t":"أَغْنِيَآءُ ۘ","c":"w"}]},{"words":[{"t":"سَنَكْتُبُ","c":"w"},{"t":"مَا","c":"w"},{"t":"قَالُوا۟","c":"w"},{"t":"وَقَتْلَهُمُ","c":"w"},{"t":"ٱلْأَنۢبِيَآءَ","c":"w"},{"t":"بِغَيْرِ","c":"w"},{"t":"حَقٍّۢ","c":"w"},{"t":"وَنَقُولُ","c":"w"}]},{"words":[{"t":"ذُوقُوا۟","c":"w"},{"t":"عَذَابَ","c":"w"},{"t":"ٱلْحَرِيقِ","c":"w"},{"t":"١٨١","c":"e"},{"t":"ذَٰلِكَ","c":"w"},{"t":"بِمَا","c":"w"},{"t":"قَدَّمَتْ","c":"w"},{"t":"أَيْدِيكُمْ","c":"w"}]},{"words":[{"t":"وَأَنَّ","c":"w"},{"t":"ٱللَّهَ","c":"w"},{"t":"لَيْسَ","c":"w"},{"t":"بِظَلَّامٍۢ","c":"w"},{"t":"لِّلْعَبِيدِ","c":"w"},{"t":"١٨٢","c":"e"},{"t":"ٱلَّذِينَ","c":"w"},{"t":"قَالُوٓا۟","c":"w"},{"t":"إِنَّ","c":"w"}]},{"words":[{"t":"ٱللَّهَ","c":"w"},{"t":"عَهِدَ","c":"w"},{"t":"إِلَيْنَآ","c":"w"},{"t":"أَلَّا","c":"w"},{"t":"نُؤْمِنَ","c":"w"},{"t":"لِرَسُولٍ","c":"w"},{"t":"حَتَّىٰ","c":"w"},{"t":"يَأْتِيَنَا","c":"w"},{"t":"بِقُرْبَانٍۢ","c":"w"}]},{"words":[{"t":"تَأْكُلُهُ","c":"w"},{"t":"ٱلنَّارُ ۗ","c":"w"},{"t":"قُلْ","c":"w"},{"t":"قَدْ","c":"w"},{"t":"جَآءَكُمْ","c":"w"},{"t":"رُسُلٌۭ","c":"w"},{"t":"مِّن","c":"w"},{"t":"قَبْلِى","c":"w"},{"t":"بِٱلْبَيِّنَـٰتِ","c":"w"}]},{"words":[{"t":"وَبِٱلَّذِى","c":"w"},{"t":"قُلْتُمْ","c":"w"},{"t":"فَلِمَ","c":"w"},{"t":"قَتَلْتُمُوهُمْ","c":"w"},{"t":"إِن","c":"w"},{"t":"كُنتُمْ","c":"w"},{"t":"صَـٰدِقِينَ","c":"w"},{"t":"١٨٣","c":"e"}]},{"words":[{"t":"فَإِن","c":"w"},{"t":"كَذَّبُوكَ","c":"w"},{"t":"فَقَدْ","c":"w"},{"t":"كُذِّبَ","c":"w"},{"t":"رُسُلٌۭ","c":"w"},{"t":"مِّن","c":"w"},{"t":"قَبْلِكَ","c":"w"},{"t":"جَآءُو","c":"w"},{"t":"بِٱلْبَيِّنَـٰتِ","c":"w"}]},{"words":[{"t":"وَٱلزُّبُرِ","c":"w"},{"t":"وَٱلْكِتَـٰبِ","c":"w"},{"t":"ٱلْمُنِيرِ","c":"w"},{"t":"١٨٤","c":"e"},{"t":"كُلُّ","c":"w"},{"t":"نَفْسٍۢ","c":"w"},{"t":"ذَآئِقَةُ","c":"w"},{"t":"ٱلْمَوْتِ ۗ","c":"w"}]},{"words":[{"t":"وَإِنَّمَا","c":"w"},{"t":"تُوَفَّوْنَ","c":"w"},{"t":"أُجُورَكُمْ","c":"w"},{"t":"يَوْمَ","c":"w"},{"t":"ٱلْقِيَـٰمَةِ ۖ","c":"w"},{"t":"فَمَن","c":"w"},{"t":"زُحْزِحَ","c":"w"}]},{"words":[{"t":"عَنِ","c":"w"},{"t":"ٱلنَّارِ","c":"w"},{"t":"وَأُدْخِلَ","c":"w"},{"t":"ٱلْجَنَّةَ","c":"w"},{"t":"فَقَدْ","c":"w"},{"t":"فَازَ ۗ","c":"w"},{"t":"وَمَا","c":"w"},{"t":"ٱلْحَيَوٰةُ","c":"w"},{"t":"ٱلدُّنْيَآ","c":"w"}]},{"words":[{"t":"إِلَّا","c":"w"},{"t":"مَتَـٰعُ","c":"w"},{"t":"ٱلْغُرُورِ","c":"w"},{"t":"١٨٥","c":"e"},{"t":"۞ لَتُبْلَوُنَّ","c":"w"},{"t":"فِىٓ","c":"w"},{"t":"أَمْوَٰلِكُمْ","c":"w"}]},{"words":[{"t":"وَأَنفُسِكُمْ","c":"w"},{"t":"وَلَتَسْمَعُنَّ","c":"w"},{"t":"مِنَ","c":"w"},{"t":"ٱلَّذِينَ","c":"w"},{"t":"أُوتُوا۟","c":"w"},{"t":"ٱلْكِتَـٰبَ","c":"w"}]},{"words":[{"t":"مِن","c":"w"},{"t":"قَبْلِكُمْ","c":"w"},{"t":"وَمِنَ","c":"w"},{"t":"ٱلَّذِينَ","c":"w"},{"t":"أَشْرَكُوٓا۟","c":"w"},{"t":"أَذًۭى","c":"w"},{"t":"كَثِيرًۭا ۚ","c":"w"}]},{"words":[{"t":"وَإِن","c":"w"},{"t":"تَصْبِرُوا۟","c":"w"},{"t":"وَتَتَّقُوا۟","c":"w"},{"t":"فَإِنَّ","c":"w"},{"t":"ذَٰلِكَ","c":"w"},{"t":"مِنْ","c":"w"},{"t":"عَزْمِ","c":"w"},{"t":"ٱلْأُمُورِ","c":"w"},{"t":"١٨٦","c":"e"}]}]}